{
  "scf_control_id": "AST-26",
  "total": 1,
  "assessment_objectives": [
    {
      "scf_control_id": "AST-26",
      "ao_id": "AST-26_A01",
      "objective": "system administration processes, with corresponding Standardized Operating Procedures (SOP), are developed, implemented and governed for operating and maintaining systems, applications and services.",
      "pptdf": "Process",
      "origin": "SCF Created",
      "assessment_rigor": "1",
      "scf_defined_parameters": "",
      "org_defined_parameters": ""
    }
  ]
}