{
  "scf_control_id": "CHG-02",
  "total": 6,
  "assessment_objectives": [
    {
      "scf_control_id": "CHG-02",
      "ao_id": "CHG-02_A01",
      "objective": "changes to the system are reviewed.",
      "pptdf": "Process",
      "origin": "171A_3.4.3[b]",
      "assessment_rigor": "1",
      "scf_defined_parameters": "",
      "org_defined_parameters": ""
    },
    {
      "scf_control_id": "CHG-02",
      "ao_id": "CHG-02_A02",
      "objective": "changes to the system are approved or disapproved.",
      "pptdf": "Process",
      "origin": "171A_3.4.3[c]",
      "assessment_rigor": "1",
      "scf_defined_parameters": "",
      "org_defined_parameters": ""
    },
    {
      "scf_control_id": "CHG-02",
      "ao_id": "CHG-02_A03",
      "objective": "approved configuration-controlled changes to the system are implemented.",
      "pptdf": "Process",
      "origin": "171A_R3_A.03.04.03.c[01]",
      "assessment_rigor": "1",
      "scf_defined_parameters": "",
      "org_defined_parameters": ""
    },
    {
      "scf_control_id": "CHG-02",
      "ao_id": "CHG-02_A04",
      "objective": "changes to the system are logged.",
      "pptdf": "Process",
      "origin": "171A_3.4.3[d]",
      "assessment_rigor": "2",
      "scf_defined_parameters": "",
      "org_defined_parameters": ""
    },
    {
      "scf_control_id": "CHG-02",
      "ao_id": "CHG-02_A05",
      "objective": "changes to the system are tracked.",
      "pptdf": "Process",
      "origin": "171A_3.4.3[a]",
      "assessment_rigor": "2",
      "scf_defined_parameters": "",
      "org_defined_parameters": ""
    },
    {
      "scf_control_id": "CHG-02",
      "ao_id": "CHG-02_A06",
      "objective": "the types of changes to the system that are configuration-controlled are defined.",
      "pptdf": "Process",
      "origin": "171A_R3_A.03.04.03.a",
      "assessment_rigor": "2",
      "scf_defined_parameters": "",
      "org_defined_parameters": ""
    }
  ]
}