{
  "scf_control_id": "DCH-06.5",
  "total": 2,
  "assessment_objectives": [
    {
      "scf_control_id": "DCH-06.5",
      "ao_id": "DCH-06.5_A01",
      "objective": "the storage of sensitive authentication data after authorization is prohibited.",
      "pptdf": "Technology",
      "origin": "SCF Created",
      "assessment_rigor": "1",
      "scf_defined_parameters": "",
      "org_defined_parameters": ""
    },
    {
      "scf_control_id": "DCH-06.5",
      "ao_id": "DCH-06.5_A02",
      "objective": "secure baseline configurations ensure authentication data is not stored after authorization.",
      "pptdf": "Technology",
      "origin": "SCF Created",
      "assessment_rigor": "1",
      "scf_defined_parameters": "",
      "org_defined_parameters": ""
    }
  ]
}