{
  "scf_control_id": "IRO-10.1",
  "total": 2,
  "assessment_objectives": [
    {
      "scf_control_id": "IRO-10.1",
      "ao_id": "IRO-10.1_A01",
      "objective": "automated mechanisms used for reporting incidents are defined.",
      "pptdf": "Process",
      "origin": "53A_R5_IR-06(01)_ODP",
      "assessment_rigor": "1",
      "scf_defined_parameters": "",
      "org_defined_parameters": ""
    },
    {
      "scf_control_id": "IRO-10.1",
      "ao_id": "IRO-10.1_A02",
      "objective": "incidents are reported using automated mechanisms.",
      "pptdf": "Technology",
      "origin": "53A_R5_IR-06(01)",
      "assessment_rigor": "1",
      "scf_defined_parameters": "",
      "org_defined_parameters": ""
    }
  ]
}