{
  "scf_control_id": "PES-06.4",
  "total": 4,
  "assessment_objectives": [
    {
      "scf_control_id": "PES-06.4",
      "ao_id": "PES-06.4_A01",
      "objective": "automated mechanisms used to maintain visitor access records are defined.",
      "pptdf": "Process",
      "origin": "53A_R5_PE-08(01)_ODP[01]",
      "assessment_rigor": "1",
      "scf_defined_parameters": "",
      "org_defined_parameters": ""
    },
    {
      "scf_control_id": "PES-06.4",
      "ao_id": "PES-06.4_A02",
      "objective": "automated mechanisms used to review visitor access records are defined.",
      "pptdf": "Process",
      "origin": "53A_R5_PE-08(01)_ODP[02]",
      "assessment_rigor": "1",
      "scf_defined_parameters": "",
      "org_defined_parameters": ""
    },
    {
      "scf_control_id": "PES-06.4",
      "ao_id": "PES-06.4_A03",
      "objective": "visitor access records are maintained using automated mechanisms.",
      "pptdf": "Technology",
      "origin": "53A_R5_PE-08(01)[01]",
      "assessment_rigor": "1",
      "scf_defined_parameters": "",
      "org_defined_parameters": ""
    },
    {
      "scf_control_id": "PES-06.4",
      "ao_id": "PES-06.4_A04",
      "objective": "visitor access records are reviewed using automated mechanisms.",
      "pptdf": "Process",
      "origin": "53A_R5_PE-08(01)[02]",
      "assessment_rigor": "1",
      "scf_defined_parameters": "",
      "org_defined_parameters": ""
    }
  ]
}